redis_cli_cluster/__init__.py
redis_cli_cluster/__main__.py
redis_cli_cluster/cluster.py
redis_cli_cluster-0.6.1.dist-info/DESCRIPTION.rst
redis_cli_cluster-0.6.1.dist-info/METADATA
redis_cli_cluster-0.6.1.dist-info/RECORD
redis_cli_cluster-0.6.1.dist-info/WHEEL
redis_cli_cluster-0.6.1.dist-info/entry_points.txt
redis_cli_cluster-0.6.1.dist-info/metadata.json
redis_cli_cluster-0.6.1.dist-info/top_level.txt
