Metadata-Version: 1.1
Name: redis-cli-cluster
Version: 0.6.1
Summary: cluster-aware redis-cli
Home-page: https://github.com/TheKevJames/redis-cli-cluster.git
Author: Kevin James
Author-email: KevinJames@thekev.in
License: MIT License
Platform: Posix; MacOS X; Windows
Classifier: Development Status :: 4 - Beta
Classifier: Intended Audience :: Developers
Classifier: Intended Audience :: End Users/Desktop
Classifier: License :: OSI Approved :: MIT License
Classifier: Natural Language :: English
Classifier: Operating System :: OS Independent
Classifier: Programming Language :: Python
Classifier: Programming Language :: Python :: 3 :: Only
